shibboleth.py
shibboleth-0.9.1.dist-info/LICENSE
shibboleth-0.9.1.dist-info/METADATA
shibboleth-0.9.1.dist-info/WHEEL
shibboleth-0.9.1.dist-info/entry_points.txt
shibboleth-0.9.1.dist-info/top_level.txt
shibboleth-0.9.1.dist-info/RECORD
