Metadata-Version: 2.1
Name: shibboleth
Version: 0.9.1
Summary: Command line tool for tracking tasks
License: BSD 3-Clause License
Keywords: cli,task,tracking,commandline,productivity
Classifier: Development Status :: 3 - Alpha
Classifier: Environment :: Console
Classifier: License :: OSI Approved :: BSD License
Classifier: Programming Language :: Python :: 3.6
Classifier: Programming Language :: Python :: 3.7
Classifier: Programming Language :: Python :: 3.8
Classifier: Programming Language :: Python :: 3.9
Classifier: Programming Language :: Python :: 3.10
Classifier: Topic :: Office/Business
Classifier: Topic :: Utilities
Requires-Python: >=3.7
License-File: LICENSE
